README.rst
setup.cfg
setup.py
fptest/__init__.py
fptest/test.py
fptest/tracing.py
fptest.egg-info/PKG-INFO
fptest.egg-info/SOURCES.txt
fptest.egg-info/dependency_links.txt
fptest.egg-info/top_level.txt