Metadata-Version: 1.1
Name: fptest
Version: 0.1.0
Summary: A TIBCO Fulfilment Provisioning test helper
Home-page: https://github.com/oxo42/FpTest
Author: John Oxley
Author-email: john.oxley@gmail.com
License: Apache
Platform: UNKNOWN
Classifier: Development Status :: 4 - Beta
Classifier: Intended Audience :: Developers
Classifier: Topic :: Software Development :: Testing
Classifier: Programming Language :: Python :: 3
Classifier: Programming Language :: Python :: 3.2
Classifier: Programming Language :: Python :: 3.3
Classifier: Programming Language :: Python :: 3.4
Classifier: Programming Language :: Python :: 3.5
Requires: lxml
Requires: requests
